{
	"description": "项目配置文件。",
	"packOptions": {
		"ignore": []
	},
	"setting": {
		"urlCheck": false,
		"es6": false,
		"postcss": false,
		"minified": false,
		"newFeature": true
	},
	"compileType": "miniprogram",
	"libVersion": "1.7.2",
	"appid": "wxeebf4ed549cf121f",
	"projectname": "%E8%B6%B3%E5%BD%A9%E8%AF%BE%E7%A8%8B",
	"svr": "",
	"client": "",
	"qcloudRoot": "",
	"miniprogramRoot": "",
	"pluginRoot": "",
	"scripts": {},
	"condition": {
		"search": {
			"current": -1,
			"list": []
		},
		"conversation": {
			"current": -1,
			"list": []
		},
		"plugin": {
			"current": -1,
			"list": []
		},
		"game": {
			"current": -1,
			"list": []
		},
		"miniprogram": {
			"current": -1,
			"list": [
				{
					"id": -1,
					"name": "课程详情页面",
					"pathName": "pages/classDetail",
					"query": "id=1"
				},
				{
					"id": -1,
					"name": "已购买课程列表",
					"pathName": "pages/meClass",
					"query": ""
				},
				{
					"id": 2,
					"name": "文章页面",
					"pathName": "pages/airticle",
					"query": "id=22"
				},
				{
					"id": -1,
					"name": "课程首页",
					"pathName": "pages/class",
					"query": ""
				},
				{
					"id": -1,
					"name": "文章页面",
					"pathName": "pages/result",
					"query": "id=22"
				},
				{
					"id": -1,
					"name": "筛选",
					"pathName": "pages/shaixuan",
					"query": ""
				}
			]
		}
	}
}